magicicadaprotocol/__init__.py
magicicadaprotocol/client.py
magicicadaprotocol/content_hash.py
magicicadaprotocol/context.py
magicicadaprotocol/delta.py
magicicadaprotocol/dircontent.py
magicicadaprotocol/dircontent_pb2.py
magicicadaprotocol/errors.py
magicicadaprotocol/protocol_pb2.py
magicicadaprotocol/proxy_tunnel.py
magicicadaprotocol/public_file_info.py
magicicadaprotocol/request.py
magicicadaprotocol/sharersp.py
magicicadaprotocol/utils.py
magicicadaprotocol/validators.py
magicicadaprotocol/volumes.py
magicicadaprotocol/tests/__init__.py
magicicadaprotocol/tests/test_bytesproducer.py
magicicadaprotocol/tests/test_client.py
magicicadaprotocol/tests/test_context.py
magicicadaprotocol/tests/test_delta_info.py
magicicadaprotocol/tests/test_dircontent.py
magicicadaprotocol/tests/test_errors.py
magicicadaprotocol/tests/test_getcontent.py
magicicadaprotocol/tests/test_hashes.py
magicicadaprotocol/tests/test_proxy_tunnel.py
magicicadaprotocol/tests/test_public_file_info.py
magicicadaprotocol/tests/test_putcontent.py
magicicadaprotocol/tests/test_query.py
magicicadaprotocol/tests/test_request.py
magicicadaprotocol/tests/test_sharersp.py
magicicadaprotocol/tests/test_throttling.py
magicicadaprotocol/tests/test_volumes.py
magicicadaprotocol-3.0.3.dist-info/COPYING
magicicadaprotocol-3.0.3.dist-info/LICENSE
magicicadaprotocol-3.0.3.dist-info/LICENSE.OpenSSL
magicicadaprotocol-3.0.3.dist-info/METADATA
magicicadaprotocol-3.0.3.dist-info/WHEEL
magicicadaprotocol-3.0.3.dist-info/top_level.txt
magicicadaprotocol-3.0.3.dist-info/RECORD
